LICENSE
README.md
setup.py
CVE_2018_8033.egg-info/PKG-INFO
CVE_2018_8033.egg-info/SOURCES.txt
CVE_2018_8033.egg-info/dependency_links.txt
CVE_2018_8033.egg-info/entry_points.txt
CVE_2018_8033.egg-info/requires.txt
CVE_2018_8033.egg-info/top_level.txt
cve20188033/__init__.py
cve20188033/main.py
cve20188033/includes/__init__.py
cve20188033/includes/bot.py
cve20188033/includes/filereader.py
cve20188033/includes/scan.py
cve20188033/includes/writefile.py
cve20188033/utils/__init__.py
cve20188033/utils/configure.py
cve20188033/utils/const.py
cve20188033/utils/helpers.py
cve20188033/utils/status.py